{"meta":{"last_updated":"2021-01-21T10:07:10.058Z","total":51,"credits":"PHPID Community"},"data":[{"id":"51","date":"Rabu, 27 Januari 2021","time":"19:00","speaker":"Petra Novandi Baru","slide":"empty","topic":"PHP Native Series: PDO & MySQL","videos":["empty"],"registrasi":"empty","cover":"https://github.com/phpid-jakarta/phpid-online-learning-2020/raw/master/cover/51.jpg","deskripsi":"-"},{"id":"50","date":"Selasa, 26 Januari 2021","time":"19:00","speaker":"Gunawan Wibisono","slide":"empty","topic":"Amazon Simple Storage Service (S3) For PHP Developer","videos":["empty"],"registrasi":"empty","cover":"https://github.com/phpid-jakarta/phpid-online-learning-2020/raw/master/cover/50.jpg","deskripsi":"-"},{"id":"49","date":"Kamis, 22 Oktober 2020","time":"19:00","speaker":"Rio Astamal","slide":"empty","topic":"Static Wordpress Hosting dengan S3 dan CloudFront","videos":["empty"],"registrasi":"https://www.facebook.com/events/1744900422345766","cover":"https://github.com/phpid-jakarta/phpid-online-learning-2020/raw/master/cover/49.jpg","deskripsi":"-"},{"id":"48","date":"Minggu, 4 Oktober 2020","time":"18:30","speaker":"Kabul Kurniawan","slide":"empty","topic":"Mengenal Teknologi Web Terdesentralisasi","videos":["empty"],"registrasi":"https://fb.me/e/8cHqQSY9S","cover":"https://github.com/phpid-jakarta/phpid-online-learning-2020/raw/master/cover/48.jpg","deskripsi":"-"},{"id":"47","date":"Jumat, 18 September 2020","time":"18:00","speaker":"Petra Novandi Barus","slide":"empty","topic":"Membangun Aplikasi Laravel Microservices dengan AWS","videos":["empty"],"registrasi":"empty","cover":"https://github.com/phpid-jakarta/phpid-online-learning-2020/raw/master/cover/47.jpg","deskripsi":""},{"id":"46","date":"Minggu, 6 September 2020","time":"18:30","speaker":"Nur Hidayat","slide":"empty","topic":"Optimizing & Scaling MySQL Web Application","videos":["https://web.facebook.com/groups/phpid/permalink/10158547046866101/"],"registrasi":"empty","cover":"https://github.com/phpid-jakarta/phpid-online-learning-2020/raw/master/cover/46.jpg","deskripsi":""},{"id":"45","date":"Minggu, 16 Agustus 2020","time":"19:00","speaker":"Juwita Sihombing","slide":"empty","topic":"How to Become a Solution Analyst for Banking Industry","videos":["empty"],"registrasi":"empty","cover":"https://github.com/phpid-jakarta/phpid-online-learning-2020/raw/master/cover/45.jpg","deskripsi":""},{"id":"44","date":"Sabtu, 8 Agustus 2020","time":"19:00","speaker":"Imam Aris Munandar","slide":"empty","topic":"Data Science Methodology","videos":["https://www.facebook.com/groups/phpid/permalink/10158471678691101/"],"registrasi":"empty","cover":"https://github.com/phpid-jakarta/phpid-online-learning-2020/raw/master/cover/44.jpg","deskripsi":""},{"id":"43","date":"Sabtu, 1 Agustus 2020","time":"19:00","speaker":"Anne Regina","slide":"empty","topic":"Anak IT merasa salah jurusan?","videos":["https://www.facebook.com/peterjkambey/videos/10220309143376497/"],"registrasi":"empty","cover":"https://github.com/phpid-jakarta/phpid-online-learning-2020/raw/master/cover/43.jpg","deskripsi":"How to survive and be a champion in the Technology fields berdasarkan pengalaman, pengamatan, pembelajaran pemateri"},{"id":"42","date":"Sabtu, 25 Juli 2020","time":"19:00","speaker":"Luri Darmawan","slide":"empty","topic":"Ask Me Anything with Om Luri Darmawan","videos":["https://web.facebook.com/peterjkambey/videos/10220255840643962/"],"registrasi":"empty","cover":"https://github.com/phpid-jakarta/phpid-online-learning-2020/raw/master/cover/42.jpg","deskripsi":"Ask Me Anything with om Luri Darmawan. Founder Carik ChatBot paling fenomenal 2020 didaftar di 1000 group telegram/wa/line/messenger."},{"id":"41","date":"Kamis, 16 Juli 2020","time":"19:00","speaker":"Arga Dinata","slide":"https://www.facebook.com/groups/phpid/permalink/10158405253286101/","topic":"Belajar Konsep CRM & Menggunakan Software CRM Gratis","videos":["https://www.facebook.com/peterjkambey/videos/10220185761212020"],"registrasi":"empty","cover":"https://github.com/phpid-jakarta/phpid-online-learning-2020/raw/master/cover/41.jpg","deskripsi":"Om Arga Dinata, Konsultan Senior yang banyak menggarap proyek2 CRM di perusahaan-perusahaan terkenal"},{"id":"40","date":"Selasa, 14 Juli 2020","time":"19:00","speaker":"Freddy Munandar - Sarccom","slide":"https://www.linkedin.com/posts/activity-6688998406926536704-KmYM","topic":"The Journey of Test-Driven Development","videos":["https://www.facebook.com/peterjkambey/videos/10220170296345408"],"registrasi":"empty","cover":"https://github.com/phpid-jakarta/phpid-online-learning-2020/raw/master/cover/40.jpg","deskripsi":"Om Freddy Founder Senior Developer, Founder/Pengurus SARCCOM - Software Architect Indonesia Community"},{"id":"39","date":"Kamis, 9 Juli 2020","time":"19:00","speaker":"Petra Novandi Barus","slide":"empty","topic":"Mendeploy Situs Wordpress yang Scalable di AWS","videos":["https://www.facebook.com/peterjkambey/videos/10220133445224153"],"registrasi":"empty","cover":"https://github.com/phpid-jakarta/phpid-online-learning-2020/raw/master/cover/39.jpg","deskripsi":"-"},{"id":"38","date":"Sabtu, 4 Juli 2020","time":"19:00","speaker":"Galih Pratama","slide":"empty","topic":"Developer Jadi Pengajar, Why Not?","videos":["https://www.facebook.com/peterjkambey/videos/10220092304035649"],"registrasi":"empty","cover":"https://github.com/phpid-jakarta/phpid-online-learning-2020/raw/master/cover/38.jpg","deskripsi":"-"},{"id":"37","date":"Sabtu, 27 Juni 2020","time":"19:00","speaker":"Muhamad Surya Iksanudin","slide":"empty","topic":"2021, PHP masih cocok untuk dipelajari?","videos":["https://www.facebook.com/peterjkambey/videos/10220026566992264"],"registrasi":"empty","cover":"https://github.com/phpid-jakarta/phpid-online-learning-2020/raw/master/cover/37.jpg","deskripsi":"-"},{"id":"36","date":"Senin, 29 Juni 2020","time":"19:00","speaker":"Om Petra Novandi Barus - AWS","slide":"empty","topic":"Membuat Aplikasi PHP Microservices dengan AWS (cancelled)","videos":["empty"],"registrasi":"empty","cover":"https://github.com/phpid-jakarta/phpid-online-learning-2020/raw/master/cover/36.jpg","deskripsi":"-"},{"id":"35","date":"Sabtu, 20 Juni 2020","time":"19:00","speaker":"Om Eryk Pratama","slide":"empty","topic":"Enabling Data Governance","videos":["https://www.facebook.com/peterjkambey/videos/10219963481295161"],"registrasi":"empty","cover":"https://github.com/phpid-jakarta/phpid-online-learning-2020/raw/master/cover/35.jpg","deskripsi":"-"},{"id":"34","date":"Minggu, 14 Juni 2020","time":"19:00","speaker":"Om Munir AP","slide":"empty","topic":"Why developer must care about Open Source?","videos":["https://www.facebook.com/peterjkambey/videos/10219914973922507"],"registrasi":"empty","cover":"https://github.com/phpid-jakarta/phpid-online-learning-2020/raw/master/cover/34.jpg","deskripsi":"-"},{"id":"33","date":"Sabtu, 13 Juni 2020","time":"19:00","speaker":"Om Prayudi Utomo","slide":"empty","topic":"Web Accessibility","videos":["https://www.facebook.com/peterjkambey/videos/10219905788772884"],"registrasi":"empty","cover":"https://github.com/phpid-jakarta/phpid-online-learning-2020/raw/master/cover/33.jpg","deskripsi":"-"},{"id":"32","date":"Kamis, 11 Juni 2020","time":"19:00","speaker":"Om Firman Brillian","slide":"empty","topic":"Python For Data Science","videos":["https://www.facebook.com/peterjkambey/videos/10219888776907598"],"registrasi":"empty","cover":"https://github.com/phpid-jakarta/phpid-online-learning-2020/raw/master/cover/32.jpg","deskripsi":"-"},{"id":"31","date":"Selasa, 9 Juni 2020","time":"19:00","speaker":"Om Buyung Bahari","slide":"empty","topic":"Software Estimation Jump Start","videos":["https://www.facebook.com/peterjkambey/videos/10219872592703003"],"registrasi":"empty","cover":"https://github.com/phpid-jakarta/phpid-online-learning-2020/raw/master/cover/31.jpg","deskripsi":"-"},{"id":"30","date":"Senin, 8 Juni 2020","time":"19:00","speaker":"Om Petra Novandi Barus - AWS","slide":"empty","topic":"Scaling Application to 1 Millions Users","videos":["https://www.facebook.com/peterjkambey/videos/10219864037649132"],"registrasi":"empty","cover":"https://github.com/phpid-jakarta/phpid-online-learning-2020/raw/master/cover/30.jpg","deskripsi":"-"},{"id":"29","date":"Sabtu, 6 Juni 2020","time":"19:00","speaker":"Om Steven Salim","slide":"empty","topic":"The Change Maker Framework","videos":["https://www.facebook.com/peterjkambey/videos/10219845832474014"],"registrasi":"empty","cover":"https://github.com/phpid-jakarta/phpid-online-learning-2020/raw/master/cover/29.jpg","deskripsi":"-"},{"id":"28","date":"Senin, 1 Juni 2020","time":"18:00","speaker":"om Peter Kambey - Om Nur Hidayat","slide":"empty","topic":"Ngobrol Santai Bareng om Peter - 2 Jam Bikin Aplikasi Absensi Online","videos":["https://www.facebook.com/peterjkambey/videos/10219798560652248"],"registrasi":"empty","cover":"https://github.com/phpid-jakarta/phpid-online-learning-2020/raw/master/cover/28.jpg","deskripsi":"-"},{"id":"27","date":"Senin, 18 Mei 2020","time":"16:00","speaker":"om Sony A Kurniawan","slide":"empty","topic":"Ngobrol Santai Bareng om Sony Kurniawan","videos":["https://www.facebook.com/peterjkambey/videos/10219674327906507"],"registrasi":"empty","cover":"https://github.com/phpid-jakarta/phpid-online-learning-2020/raw/master/cover/27.jpg","deskripsi":"-"},{"id":"23","date":"Minggu, 17 Mei 2020","time":"16:30","speaker":"om Sastra Nababan","slide":"empty","topic":"Live Coding Music - Write Music with Code","videos":["https://www.facebook.com/peterjkambey/videos/10219664721066342"],"registrasi":"empty","cover":"https://github.com/phpid-jakarta/phpid-online-learning-2020/raw/master/cover/23.jpg","deskripsi":"-"},{"id":"24","date":"Sabtu, 16 Mei 2020","time":"16:00","speaker":"om Stenly Karouw","slide":"empty","topic":"Pengembangan Sistem Informasi eGovernment (cancelled)","videos":["empty"],"registrasi":"empty","cover":"https://github.com/phpid-jakarta/phpid-online-learning-2020/raw/master/cover/not-found.jpg","deskripsi":"-"},{"id":"26","date":"Jumat, 15 Mei 2020","time":"16:00","speaker":"om Kresna Galuh","slide":"https://docs.google.com/presentation/d/1Z4LHVF4_PRM0D1iHjdPiGaETyBS0kfbLoVT3vckabB0/edit?usp=sharing","topic":"Codepolitan","videos":["https://www.facebook.com/peterjkambey/videos/10219644689445564"],"registrasi":"empty","cover":"https://github.com/phpid-jakarta/phpid-online-learning-2020/raw/master/cover/26.jpg","deskripsi":"-"},{"id":"25","date":"Kamis, 14 Mei 2020","time":"16:00","speaker":"om Abdul Hadi","slide":"empty","topic":"PostgreSQL: DDL dan SQL","videos":["https://www.facebook.com/peterjkambey/videos/10219634513351168"],"registrasi":"empty","cover":"https://github.com/phpid-jakarta/phpid-online-learning-2020/raw/master/cover/25.jpg","deskripsi":"-"},{"id":"22","date":"Senin, 11 Mei 2020","time":"16:00","speaker":"Ibu Falahah - Dosen Univ. Telkom Bandung","slide":"https://speakerdeck.com/flash68/system-analyst-short-guide","topic":"The Practical Guide howto become System Analyst","videos":["https://www.facebook.com/peterjkambey/videos/10219608505780995"],"registrasi":"empty","cover":"https://github.com/phpid-jakarta/phpid-online-learning-2020/raw/master/cover/22.jpg","deskripsi":"-"},{"id":"21","date":"Sabtu, 9 Mei 2020","time":"16:00","speaker":"om Musa Amin","slide":"https://musaamin.web.id/wp-content/uploads/2020/05/Linux-Server-untuk-Aplikasi-PHP.pdf","topic":"Linux Server for PHP Developer","videos":["https://www.facebook.com/peterjkambey/videos/10219586488470576"],"registrasi":"empty","cover":"https://github.com/phpid-jakarta/phpid-online-learning-2020/raw/master/cover/21.jpg","deskripsi":"-"},{"id":"20","date":"Jumat, 8 Mei 2020","time":"16:00","speaker":"om Nur Hidayah","slide":"https://www.slideshare.net/hidayat365/do-it-with-sql-journey-to-the-center-of-database-worlds","topic":"Do it with SQL - Journey to the Center of Database World","videos":["https://www.facebook.com/peterjkambey/videos/10219575493195701"],"registrasi":"empty","cover":"https://github.com/phpid-jakarta/phpid-online-learning-2020/raw/master/cover/20.jpg","deskripsi":"-"},{"id":"19","date":"Kamis, 7 Mei 2020","time":"16:00","speaker":"om Dyan Galih","slide":"empty","topic":"Personal Security Awareness","videos":["https://www.facebook.com/peterjkambey/videos/10219564541841924"],"registrasi":"empty","cover":"https://github.com/phpid-jakarta/phpid-online-learning-2020/raw/master/cover/19.jpg","deskripsi":"-"},{"id":"18","date":"Rabu, 6 Mei 2020","time":"16:30","speaker":"Om Fitra Aditya","slide":"https://docs.google.com/presentation/d/1rT4BSSXCYEzF9eCQJ1Bbnr65p2LZtMndrENzNQNN4Q8/edit?usp=sharing","topic":"Web RTC","videos":["https://www.facebook.com/peterjkambey/videos/10219553693850731"],"registrasi":"empty","cover":"https://github.com/phpid-jakarta/phpid-online-learning-2020/raw/master/cover/18.jpg","deskripsi":"-"},{"id":"17","date":"Selasa, 5 Mei 2020","time":"16:30","speaker":"Ali Pasha - GeekHunter","slide":"empty","topic":"How to Secure your Next Job During Covid-19 Pandemic","videos":["https://www.facebook.com/peterjkambey/videos/10219542443169471"],"registrasi":"empty","cover":"https://github.com/phpid-jakarta/phpid-online-learning-2020/raw/master/cover/17.jpg","deskripsi":"-"},{"id":"16","date":"Senin, 4 Mei 2020","time":"16:00","speaker":"om Prasetyo Wicaksono","slide":"empty","topic":"Evolution Of PHP","videos":["https://www.facebook.com/peterjkambey/videos/10219532379837894"],"registrasi":"empty","cover":"https://github.com/phpid-jakarta/phpid-online-learning-2020/raw/master/cover/16.jpg","deskripsi":"-"},{"id":"15","date":"Minggu, 3 Mei 2020","time":"16:30","speaker":"Shindu Samodra","slide":"empty","topic":"Rest API dengan PHP OOP","videos":["https://www.facebook.com/peterjkambey/videos/10219521400483417"],"registrasi":"empty","cover":"https://github.com/phpid-jakarta/phpid-online-learning-2020/raw/master/cover/15.jpg","deskripsi":"-"},{"id":"14","date":"Sabtu, 2 Mei 2020","time":"16:30","speaker":"Agit Naeta","slide":"empty","topic":"Tactics and Strategy to Define Digital Products","videos":["https://www.facebook.com/peterjkambey/videos/10219510663695004"],"registrasi":"empty","cover":"https://github.com/phpid-jakarta/phpid-online-learning-2020/raw/master/cover/14.jpg","deskripsi":"-"},{"id":"13","date":"Kamis, 30 April 2020","time":"16:30","speaker":"Om Frangky Tumiwan","slide":"empty","topic":"Remote Worker","videos":["https://www.facebook.com/peterjkambey/videos/10219491497055850"],"registrasi":"empty","cover":"https://github.com/phpid-jakarta/phpid-online-learning-2020/raw/master/cover/13.jpg","deskripsi":"-"},{"id":"12","date":"Selasa, 28 April 2020","time":"16:30","speaker":"Randy Vianda Putra","slide":"https://speakerdeck.com/randyviandaputra/berkarir-sebagai-frontend-developer","topic":"Berkarir sebagai Frontend Developer","videos":["https://www.facebook.com/peterjkambey/videos/10219471755322319"],"registrasi":"empty","cover":"https://github.com/phpid-jakarta/phpid-online-learning-2020/raw/master/cover/12.jpg","deskripsi":"-"},{"id":"11","date":"Minggu, 26 April 2020","time":"16:30","speaker":"Firman Brilian","slide":"empty","topic":"Starting Your Career in the Data Science","videos":["https://www.facebook.com/peterjkambey/videos/10219460519601433"],"registrasi":"empty","cover":"https://github.com/phpid-jakarta/phpid-online-learning-2020/raw/master/cover/11.jpg","deskripsi":"-"},{"id":"10","date":"Sabtu, 25 April 2020","time":"16:30","speaker":"Munir AP","slide":"empty","topic":"Optimize Image on Your Website 101","videos":["https://www.facebook.com/peterjkambey/videos/10219439233869303"],"registrasi":"empty","cover":"https://github.com/phpid-jakarta/phpid-online-learning-2020/raw/master/cover/10.jpg","deskripsi":"-"},{"id":"9","date":"Jumat, 24 April 2020","time":"16:30","speaker":"Petra Barus","slide":"empty","topic":"Building CI/CD Pipeline","videos":["https://www.facebook.com/peterjkambey/videos/10219428640684480"],"registrasi":"empty","cover":"https://github.com/phpid-jakarta/phpid-online-learning-2020/raw/master/cover/9.jpg","deskripsi":"-"},{"id":"8","date":"Rabu, 22 April 2020","time":"19:30","speaker":"Fadhil Zikri Muhammad","slide":"empty","topic":"Social Media Digital Strategy","videos":["https://www.facebook.com/peterjkambey/videos/10219410023379059"],"registrasi":"empty","cover":"https://github.com/phpid-jakarta/phpid-online-learning-2020/raw/master/cover/8.jpg","deskripsi":"-"},{"id":"7","date":"Minggu, 19 April 2020","time":"19:30","speaker":"Muhammad Amirul Ihsan","slide":"empty","topic":"Laravel LiveWire 101","videos":["https://www.facebook.com/peterjkambey/videos/10219376923231576"],"registrasi":"empty","cover":"https://github.com/phpid-jakarta/phpid-online-learning-2020/raw/master/cover/7.jpg","deskripsi":"-"},{"id":"6","date":"Kamis, 16 April 2020","time":"19:30","speaker":"Achmad Mardiansyah","slide":"empty","topic":"Migration from Procedural to OOP","videos":["https://www.facebook.com/peterjkambey/videos/10219344732706833"],"registrasi":"empty","cover":"https://github.com/phpid-jakarta/phpid-online-learning-2020/raw/master/cover/6.jpg","deskripsi":"-"},{"id":"5","date":"Rabu, 15 April 2020","time":"19:30","speaker":"Wiguno","slide":"empty","topic":"Why Documentation Matter","videos":["https://www.facebook.com/peterjkambey/videos/10219333692590837"],"registrasi":"empty","cover":"https://github.com/phpid-jakarta/phpid-online-learning-2020/raw/master/cover/5.jpg","deskripsi":"-"},{"id":"4","date":"Selasa, 14 April 2020","time":"19:30","speaker":"Irfan Maulana","slide":"https://speakerdeck.com/mazipan/kinerja-web-101","topic":"Kinerja Web 101","videos":["https://www.facebook.com/peterjkambey/videos/10219322209183759"],"registrasi":"empty","cover":"https://github.com/phpid-jakarta/phpid-online-learning-2020/raw/master/cover/4.jpg","deskripsi":"-"},{"id":"3","date":"Minggu, 12 April 2020","time":"19:30","speaker":"Arbahud Rio Daroyni","slide":"https://www.linkedin.com/posts/arbahud-rio-daroyni-062100146_step-by-step-belajar-seo-dasar-activity-6655336421471158272-Sbw5","topic":"SEO Basic","videos":["https://youtu.be/emfHRGd5LuE"],"registrasi":"empty","cover":"https://github.com/phpid-jakarta/phpid-online-learning-2020/raw/master/cover/3.jpg","deskripsi":"-"},{"id":"2","date":"Jumat, 10 April 2020","time":"19:30","speaker":"Prayudi Utomo","slide":"https://speakerdeck.com/yudiutomo/ux-introduction","topic":"Coder Journey to UI/UX Galaxy","videos":["https://www.facebook.com/peterjkambey/videos/10219281729691797"],"registrasi":"empty","cover":"https://github.com/phpid-jakarta/phpid-online-learning-2020/raw/master/cover/2.jpg","deskripsi":"-"},{"id":"1","date":"Kamis, 9 April 2020","time":"19:30","speaker":"Nur Hidayat","slide":"https://slideshare.net/hidayat365/how-to-design-a-good-database","topic":"How to design a good database","videos":["https://youtu.be/fSQ8JamoAfg"],"registrasi":"empty","cover":"https://github.com/phpid-jakarta/phpid-online-learning-2020/raw/master/cover/1.jpg","deskripsi":"-"}]}